ebayfeed/__init__.py
ebayfeed/api.py
ebayfeed/categories.py
ebayfeed/constants.py
ebayfeed/credentials.py
ebayfeed/downloader.py
ebayfeed/utils.py
ebayfeed-2018.11.1.dist-info/LICENSE
ebayfeed-2018.11.1.dist-info/METADATA
ebayfeed-2018.11.1.dist-info/WHEEL
ebayfeed-2018.11.1.dist-info/top_level.txt
ebayfeed-2018.11.1.dist-info/zip-safe
ebayfeed-2018.11.1.dist-info/RECORD
