Metadata-Version: 2.1
Name: ebayfeed
Version: 2018.11.1
Summary: Download item feeds from eBay RESTful APIs.
Home-page: https://github.com/alessandrozamberletti/ebayfeed
Author: alez
Author-email: alez.pypi@gmail.com
License: MIT
Keywords: ebayfeed ebay-item-feed ebay-api ebay-rest-api ebay-oauth
Platform: UNKNOWN
Classifier: Development Status :: 5 - Production/Stable
Classifier: Intended Audience :: Developers
Classifier: License :: OSI Approved :: MIT License
Classifier: Natural Language :: English
Classifier: Programming Language :: Python :: 2.7
Classifier: Programming Language :: Python :: 3.4
Classifier: Programming Language :: Python :: 3.5
Classifier: Programming Language :: Python :: 3.6
Classifier: Programming Language :: Python :: 3.7
Classifier: Topic :: Software Development :: Libraries :: Python Modules
Classifier: Topic :: Utilities
Requires-Dist: requests
